pydpm/__init__.py
pydpm/example.py
pydpm/_metric/__init__.py
pydpm/_metric/_accuracy.py
pydpm/_metric/_reconstruction.py
pydpm/_metric/_topic_coherence.py
pydpm/_model/__init__.py
pydpm/_model/_basic_model.py
pydpm/_model/_cpfa.py
pydpm/_model/_cpgbn.py
pydpm/_model/_dirbn.py
pydpm/_model/_dpfa.py
pydpm/_model/_dpgds.py
pydpm/_model/_lda.py
pydpm/_model/_pfa.py
pydpm/_model/_pgbn.py
pydpm/_model/_pgds.py
pydpm/_model/_wedtm.py
pydpm/_sampler/__init__.py
pydpm/_sampler/_basic_sampler.py
pydpm/_sampler/_distribution_sampler_cpu.py
pydpm/_sampler/_distribution_sampler_gpu.py
pydpm/_sampler/_model_sampler_cpu.py
pydpm/_sampler/_model_sampler_gpu.py
pydpm/_sampler/_pre_process.py
pydpm/_sampler/_compact/crt_cpu.dll
pydpm/_sampler/_compact/crt_cpu.so
pydpm/_sampler/_compact/crt_multi_aug_cpu.dll
pydpm/_sampler/_compact/crt_multi_aug_cpu.so
pydpm/_sampler/_compact/multi_aug_cpu.dll
pydpm/_sampler/_compact/multi_aug_cpu.so
pydpm/_sampler/_compact/sampler_kernel_linux.cu
pydpm/_sampler/_compact/sampler_kernel_linux.h
pydpm/_sampler/_compact/sampler_kernel_win.cu
pydpm/_sampler/_compact/sampler_kernel_win.h
pydpm/_utils/__init__.py
pydpm/_utils/_utils.py
pydpmtest-0.3.0.dist-info/LICENSE
pydpmtest-0.3.0.dist-info/METADATA
pydpmtest-0.3.0.dist-info/WHEEL
pydpmtest-0.3.0.dist-info/top_level.txt
pydpmtest-0.3.0.dist-info/RECORD
