Metadata-Version: 2.1
Name: pydpmtest
Version: 0.3.0
Summary: A python library focuses on constructing deep probabilistic models on GPU.
Home-page: https://github.com/BoChenGroup/Pydpm
Author: ['Chaojie Wang', 'Wei Zhao', 'Jiawen Wu']
Author-email: xd_silly@163.com
Maintainer: BoChenGroup
License: Apache License Version 2.0
Platform: Windows
Platform: Linux
Classifier: Development Status :: 4 - Beta
Classifier: Environment :: GPU :: NVIDIA CUDA
Classifier: Operating System :: OS Independent
Classifier: Intended Audience :: Developers
Classifier: Programming Language :: Python :: 3
Classifier: Topic :: Software Development :: Libraries
Requires: numpy
Requires: scipy
License-File: LICENSE
